muttdown/__init__.py
muttdown/__main__.py
muttdown/config.py
muttdown/debug.py
muttdown/main.py
muttdown-0.4.0.dist-info/LICENSE.txt
muttdown-0.4.0.dist-info/METADATA
muttdown-0.4.0.dist-info/WHEEL
muttdown-0.4.0.dist-info/entry_points.txt
muttdown-0.4.0.dist-info/top_level.txt
muttdown-0.4.0.dist-info/RECORD
