Metadata-Version: 2.1
Name: muttdown
Version: 0.4.0
Summary: Sendmail replacement that compiles markdown into HTML
Home-page: https://github.com/Roguelazer/muttdown
Author: James Brown
Author-email: roguelazer@roguelazer.com
License: ISC
Keywords: email
Classifier: Development Status :: 3 - Alpha
Classifier: Environment :: Console
Classifier: Programming Language :: Python
Classifier: Programming Language :: Python :: 3.6
Classifier: Programming Language :: Python :: 3.7
Classifier: Programming Language :: Python :: 3.8
Classifier: Programming Language :: Python :: 3.9
Classifier: Programming Language :: Python :: 3.10
Classifier: Programming Language :: Python :: 3.11
Classifier: Intended Audience :: End Users/Desktop
Classifier: Operating System :: OS Independent
Classifier: License :: OSI Approved :: ISC License (ISCL)
Classifier: Topic :: Communications :: Email
Requires-Python: >=3.6
License-File: LICENSE.txt
Requires-Dist: Markdown <4.0,>=3.0
Requires-Dist: PyYAML >=3.0
Requires-Dist: pynliner ==0.8.0
Requires-Dist: six
